{
  "$schema": "https://www.typescriptlang.org/tsconfig.schema.json",
  "compilerOptions": {
    "target": "ES2022",
    "lib": ["ES2022"],
    "module": "ESNext",
    "moduleResolution": "bundler",
    "resolveJsonModule": true,
    "allowJs": true,
    "checkJs": false,
    "jsx": "react-jsx",
    "declaration": true,
    "declarationMap": true,
    "sourceMap": true,
    "outDir": "./dist",
    "rootDir": "./src",
    "composite": true,
    "incremental": true,
    "esModuleInterop": true,
    "forceConsistentCasingInFileNames": true,
    "strict": true,
    "noUnusedLocals": true,
    "noUnusedParameters": true,
    "noFallthroughCasesInSwitch": true,
    "noUncheckedIndexedAccess": true,
    "noImplicitOverride": true,
    "skipLibCheck": true,
    "isolatedModules": true,
    "allowSyntheticDefaultImports": true
  },
  "exclude": ["node_modules", "dist"]
}
